rawr_python/__init__.py
rawr_python/classes/__init__.py
rawr_python/classes/champion_damage.py
rawr_python/classes/champion_position.py
rawr_python/classes/champion_stats.py
rawr_python/classes/damage_stats.py
rawr_python/classes/event.py
rawr_python/classes/match.py
rawr_python/classes/metadata.py
rawr_python/classes/participant.py
rawr_python/classes/participant_frame.py
rawr_python/classes/perks.py
rawr_python/classes/summoner.py
rawr_python/classes/timeline.py
rawr_python/functions.py
rawr_python/resources/__init__.py
rawr_python/resources/resources.yaml
rawr_python/utils.py
rawr_python-0.1.0.dist-info/LICENSE
rawr_python-0.1.0.dist-info/WHEEL
rawr_python-0.1.0.dist-info/METADATA
rawr_python-0.1.0.dist-info/RECORD
